openai_codex_sdk/__init__.py
openai_codex_sdk/abort.py
openai_codex_sdk/auth.py
openai_codex_sdk/codex.py
openai_codex_sdk/errors.py
openai_codex_sdk/exec.py
openai_codex_sdk/install.py
openai_codex_sdk/output_schema_file.py
openai_codex_sdk/parsing.py
openai_codex_sdk/py.typed
openai_codex_sdk/thread.py
openai_codex_sdk/types.py
openai_codex_sdk/utils.py
openai_codex_sdk/vendor/README.md
openai_codex_sdk-0.1.11.dist-info/METADATA
openai_codex_sdk-0.1.11.dist-info/WHEEL
openai_codex_sdk-0.1.11.dist-info/top_level.txt
openai_codex_sdk-0.1.11.dist-info/RECORD
