Metadata-Version: 2.4
Name: openai-codex-sdk
Version: 0.1.11
Summary: Python SDK for the OpenAI Codex CLI (wraps the bundled codex binary).
Author: OpenAI
License: Apache-2.0
Keywords: openai,codex,sdk,python,agent
Requires-Python: >=3.10
Requires-Dist: pydantic<3,>=2.7
Requires-Dist: typing_extensions>=4.10
Provides-Extra: dev
Requires-Dist: pytest>=8; extra == "dev"
Requires-Dist: pytest-asyncio>=0.23; extra == "dev"
Requires-Dist: ruff>=0.6; extra == "dev"
Requires-Dist: mypy>=1.10; extra == "dev"
